great_dictator/__init__.py
great_dictator/app.py
great_dictator/adapters/__init__.py
great_dictator/adapters/inbound/__init__.py
great_dictator/adapters/inbound/fastapi_app.py
great_dictator/adapters/outbound/__init__.py
great_dictator/adapters/outbound/whisper_transcriber.py
great_dictator/domain/__init__.py
great_dictator/domain/transcription.py
great_dictator/static/index.html
great_dictator-0.1.0.dist-info/licenses/LICENSE
great_dictator-0.1.0.dist-info/METADATA
great_dictator-0.1.0.dist-info/WHEEL
great_dictator-0.1.0.dist-info/top_level.txt
great_dictator-0.1.0.dist-info/RECORD
