Metadata-Version: 2.4
Name: great-dictator
Version: 0.1.0
Summary: A browser-based dictation engine for workstation or phone
Author-email: Romilly Cocking <romilly.cocking@gmail.com>
License: MIT
Project-URL: Homepage, https://github.com/romilly/great-dictator
Project-URL: Repository, https://github.com/romilly/great-dictator.git
Project-URL: Issues, https://github.com/romilly/great-dictator/issues
Classifier: Development Status :: 3 - Alpha
Classifier: Intended Audience :: Developers
Classifier: License :: OSI Approved :: MIT License
Classifier: Programming Language :: Python :: 3
Classifier: Programming Language :: Python :: 3.8
Classifier: Programming Language :: Python :: 3.9
Classifier: Programming Language :: Python :: 3.10
Classifier: Programming Language :: Python :: 3.11
Classifier: Programming Language :: Python :: 3.12
Requires-Python: >=3.8
License-File: LICENSE
Requires-Dist: faster-whisper
Requires-Dist: fastapi
Requires-Dist: uvicorn[standard]
Requires-Dist: python-multipart
Provides-Extra: test
Requires-Dist: pytest>=7.0.0; extra == "test"
Requires-Dist: pytest-cov; extra == "test"
Requires-Dist: pyright; extra == "test"
Requires-Dist: PyHamcrest; extra == "test"
Dynamic: license-file
